[
null,
{"id":1,"expanded":false,"name":"debug","order":1,"parentId":0,"scrollX":1092,"scrollY":614.6666666666666},
{"id":2,"expanded":true,"name":"ohouse","order":3,"parentId":0,"scrollX":1092,"scrollY":616},
{"id":3,"expanded":true,"name":"ihouse","order":6,"parentId":0,"scrollX":1228.5,"scrollY":691.5},
{"id":4,"expanded":false,"name":"pond1","order":2,"parentId":0,"scrollX":1092,"scrollY":616},
{"id":5,"expanded":false,"name":"bitcoinmineentrance","order":7,"parentId":0,"scrollX":1092,"scrollY":616},
{"id":6,"expanded":false,"name":"bitcoinmines","order":10,"parentId":0,"scrollX":1081.3333333333333,"scrollY":692},
{"id":7,"expanded":false,"name":"bitcoinbossroom","order":4,"parentId":0,"scrollX":1965.6,"scrollY":1106.3999999999999},
{"id":8,"expanded":false,"name":"snakeroom","order":5,"parentId":0,"scrollX":1092,"scrollY":616},
{"id":9,"expanded":false,"name":"amongusvillage","order":8,"parentId":0,"scrollX":1081.3333333333333,"scrollY":1304},
{"id":10,"expanded":false,"name":"inn","order":9,"parentId":0,"scrollX":1092,"scrollY":616},
{"id":11,"expanded":false,"name":"forest","order":11,"parentId":0,"scrollX":1092,"scrollY":616}
]